odoo/addons/stock_weighing_remote_measure/README.rst
odoo/addons/stock_weighing_remote_measure/__init__.py
odoo/addons/stock_weighing_remote_measure/__manifest__.py
odoo/addons/stock_weighing_remote_measure/i18n/es.po
odoo/addons/stock_weighing_remote_measure/i18n/stock_weighing_remote_measure.pot
odoo/addons/stock_weighing_remote_measure/readme/DESCRIPTION.md
odoo/addons/stock_weighing_remote_measure/readme/README.md
odoo/addons/stock_weighing_remote_measure/static/description/icon.png
odoo/addons/stock_weighing_remote_measure/static/description/index.html
odoo/addons/stock_weighing_remote_measure/static/src/js/weight_record_form_widget.esm.js
odoo/addons/stock_weighing_remote_measure/static/src/scss/weight_wizard.scss
odoo/addons/stock_weighing_remote_measure/static/src/xml/weight_record_form_widget.xml
odoo/addons/stock_weighing_remote_measure/wizards/__init__.py
odoo/addons/stock_weighing_remote_measure/wizards/weighing_wizard.py
odoo/addons/stock_weighing_remote_measure/wizards/weighing_wizard_views.xml
odoo_addon_stock_weighing_remote_measure-15.0.1.1.0.dist-info/METADATA
odoo_addon_stock_weighing_remote_measure-15.0.1.1.0.dist-info/WHEEL
odoo_addon_stock_weighing_remote_measure-15.0.1.1.0.dist-info/top_level.txt
odoo_addon_stock_weighing_remote_measure-15.0.1.1.0.dist-info/RECORD
