Metadata-Version: 2.1
Name: odoo-addon-stock_weighing_remote_measure
Version: 15.0.1.1.0
Summary: Gather the operations weights remotely
Home-page: https://github.com/OCA/stock-weighing
Author: Tecnativa, Odoo Community Association (OCA)
Author-email: support@odoo-community.org
License: AGPL-3
Classifier: Programming Language :: Python
Classifier: Framework :: Odoo
Classifier: Framework :: Odoo :: 15.0
Classifier: License :: OSI Approved :: GNU Affero General Public License v3
Requires-Python: >=3.8
Requires-Dist: odoo-addon-stock-weighing<15.1dev,>=15.0dev
Requires-Dist: odoo-addon-web-widget-remote-measure<15.1dev,>=15.0dev
Requires-Dist: odoo<15.1dev,>=15.0a
